nightfocus/.gitignore
nightfocus/__init__.py
nightfocus/camera.py
nightfocus/dataset.py
nightfocus/display.py
nightfocus/evaluation.py
nightfocus/focus_metrics.py
nightfocus/main.py
nightfocus/processing.py
nightfocus/scoring.py
nightfocus/workers.py
nightfocus-0.1.3.dist-info/METADATA
nightfocus-0.1.3.dist-info/WHEEL
nightfocus-0.1.3.dist-info/entry_points.txt
nightfocus-0.1.3.dist-info/RECORD
