Metadata-Version: 2.1
Name: nightfocus
Version: 0.1.3
Summary: autofocus algorithms for clear night sky
Author: Vincent Berenz
Author-email: vincent.berenz@tuebingen.mpg.de
Requires-Python: >=3.9,<4.0
Classifier: Programming Language :: Python :: 3
Classifier: Programming Language :: Python :: 3.9
Classifier: Programming Language :: Python :: 3.10
Classifier: Programming Language :: Python :: 3.11
Classifier: Programming Language :: Python :: 3.12
Classifier: Programming Language :: Python :: 3.13
Requires-Dist: click (==8.1.8)
Requires-Dist: loguru (>=0.7.3,<0.8.0)
Requires-Dist: matplotlib (==3.9.4)
Requires-Dist: multipledispatch (>=1.0.0,<2.0.0)
Requires-Dist: opencv-python (>=4.11.0.86,<5.0.0.0)
Requires-Dist: pillow (>=11.2.1,<12.0.0)
Requires-Dist: plotext (>=5.2.8,<6.0.0)
Requires-Dist: pytest (>=8.3.5,<9.0.0)
Requires-Dist: rich (>=14.0.0,<15.0.0)
Requires-Dist: scikit-learn (==1.6.1)
Requires-Dist: scikit-optimize (==0.10.2)
Requires-Dist: scipy (==1.13.1)
Requires-Dist: tifffile (==2024.8.30)
Requires-Dist: tqdm (>=4.67.1,<5.0.0)
Requires-Dist: types-pillow (>=10.2.0.20240822,<11.0.0.0)
Requires-Dist: types-tqdm (>=4.67.0.20250516,<5.0.0.0)
